{
  "resolvedId": "/Users/amerusfinancial/Desktop/projects/Amerus/app/components/resources/ResourceTabs.vue?nuxt_component=async&nuxt_component_name=ResourceTabs",
  "transforms": [
    {
      "name": "vite:load-fallback",
      "result": "<template>\n  <div class=\"mx-auto max-w-5xl\">\n    <div role=\"tablist\" class=\"h-10 items-center justify-center rounded-md bg-muted p-1 text-muted-foreground bg-gray-300 grid w-full grid-cols-2 mb-8\">\n      <button \n        type=\"button\" \n        :class=\"tab === 'guides' ? activeClass : inactiveClass\" \n        @click=\"tab = 'guides'\"\n      >\n        Guides & Forms\n      </button>\n      <button \n        type=\"button\" \n        :class=\"tab === 'blog' ? activeClass : inactiveClass\" \n        @click=\"tab = 'blog'\"\n      >\n        Blog\n      </button>\n    </div>\n\n    <div v-if=\"tab === 'guides'\" class=\"grid grid-cols-1 md:grid-cols-2 lg:grid-cols-3 gap-6\">\n      <slot name=\"guides\" />\n    </div>\n    <div v-else class=\"mt-2 space-y-6\">\n      <slot name=\"blog\" />\n    </div>\n  </div>\n</template>\n\n<script setup lang=\"ts\">\nimport { ref } from 'vue'\nconst tab = ref<'guides' | 'blog'>('guides')\n\nconst activeClass = 'inline-flex items-center justify-center whitespace-nowrap rounded-sm px-3 py-1.5 text-sm font-medium ring-offset-background transition-all focus-visible:outline-none focus-visible:ring-2 focus-visible:ring-ring focus-visible:ring-offset-2 bg-white text-foreground shadow-sm'\nconst inactiveClass = 'inline-flex items-center justify-center whitespace-nowrap rounded-sm px-3 py-1.5 text-sm font-medium ring-offset-background transition-all focus-visible:outline-none focus-visible:ring-2 focus-visible:ring-ring focus-visible:ring-offset-2'\n</script>\n",
      "start": 1761251140896,
      "end": 1761251141156,
      "sourcemaps": null
    },
    {
      "name": "nuxt:layer-aliasing",
      "start": 1761251141156,
      "end": 1761251141156,
      "order": "pre"
    },
    {
      "name": "nuxt:layer-aliasing",
      "start": 1761251141156,
      "end": 1761251141156,
      "order": "pre"
    },
    {
      "name": "nuxt:server-devonly:transform",
      "start": 1761251141156,
      "end": 1761251141156,
      "order": "pre"
    },
    {
      "name": "nuxt:server-devonly:transform",
      "start": 1761251141156,
      "end": 1761251141156,
      "order": "pre"
    },
    {
      "name": "content-slot",
      "start": 1761251141156,
      "end": 1761251141156,
      "order": "pre"
    },
    {
      "name": "content-slot",
      "start": 1761251141156,
      "end": 1761251141156,
      "order": "pre"
    },
    {
      "name": "nuxt:client-fallback-auto-id",
      "start": 1761251141156,
      "end": 1761251141156,
      "order": "pre"
    },
    {
      "name": "server-only-component-transform",
      "start": 1761251141156,
      "end": 1761251141156,
      "order": "pre"
    },
    {
      "name": "vite:css",
      "start": 1761251141156,
      "end": 1761251141156,
      "order": "normal"
    },
    {
      "name": "vite:esbuild",
      "start": 1761251141156,
      "end": 1761251141156,
      "order": "normal"
    },
    {
      "name": "vite:json",
      "start": 1761251141156,
      "end": 1761251141156,
      "order": "normal"
    },
    {
      "name": "vite:worker",
      "start": 1761251141156,
      "end": 1761251141156,
      "order": "normal"
    },
    {
      "name": "vite:vue",
      "result": "import _sfc_main from \"/Users/amerusfinancial/Desktop/projects/Amerus/app/components/resources/ResourceTabs.vue?vue&type=script&setup=true&lang.ts\";\nexport * from \"/Users/amerusfinancial/Desktop/projects/Amerus/app/components/resources/ResourceTabs.vue?vue&type=script&setup=true&lang.ts\";\nimport { useSSRContext as __vite_useSSRContext } from \"vue\";\nconst _sfc_setup = _sfc_main.setup;\n_sfc_main.setup = (props, ctx) => {\n  const ssrContext = __vite_useSSRContext();\n  (ssrContext.modules || (ssrContext.modules = /* @__PURE__ */ new Set())).add(\"components/resources/ResourceTabs.vue\");\n  return _sfc_setup ? _sfc_setup(props, ctx) : void 0;\n};\nexport default _sfc_main;\n",
      "start": 1761251141156,
      "end": 1761251141279,
      "order": "normal",
      "sourcemaps": {
        "mappings": ""
      }
    },
    {
      "name": "vite:vue-jsx",
      "start": 1761251141279,
      "end": 1761251141279,
      "order": "normal"
    },
    {
      "name": "replace",
      "start": 1761251141279,
      "end": 1761251141279,
      "order": "normal"
    },
    {
      "name": "replace",
      "start": 1761251141279,
      "end": 1761251141279,
      "order": "normal"
    },
    {
      "name": "nuxt:remove-plugin-metadata",
      "start": 1761251141279,
      "end": 1761251141279,
      "order": "normal"
    },
    {
      "name": "nuxt:remove-plugin-metadata",
      "start": 1761251141279,
      "end": 1761251141279,
      "order": "normal"
    },
    {
      "name": "nuxt:components:imports",
      "result": "import { defineAsyncComponent } from \"vue\"\nexport default defineAsyncComponent(() => import(\"/Users/amerusfinancial/Desktop/projects/Amerus/app/components/resources/ResourceTabs.vue\").then(r => r.default))",
      "start": 1761251141279,
      "end": 1761251141279,
      "order": "normal",
      "sourcemaps": null
    },
    {
      "name": "replace",
      "start": 1761251141279,
      "end": 1761251141280,
      "order": "normal"
    },
    {
      "name": "ssr-styles",
      "start": 1761251141280,
      "end": 1761251141280,
      "order": "normal"
    },
    {
      "name": "vite:define",
      "start": 1761251141280,
      "end": 1761251141280,
      "order": "normal"
    },
    {
      "name": "vite:css-post",
      "start": 1761251141280,
      "end": 1761251141280,
      "order": "normal"
    },
    {
      "name": "vite:build-html",
      "start": 1761251141280,
      "end": 1761251141280,
      "order": "normal"
    },
    {
      "name": "vite:worker-import-meta-url",
      "start": 1761251141280,
      "end": 1761251141280,
      "order": "normal"
    },
    {
      "name": "vite:asset-import-meta-url",
      "start": 1761251141280,
      "end": 1761251141280,
      "order": "normal"
    },
    {
      "name": "commonjs",
      "start": 1761251141280,
      "end": 1761251141280,
      "order": "normal"
    },
    {
      "name": "vite:dynamic-import-vars",
      "start": 1761251141280,
      "end": 1761251141280,
      "order": "normal"
    },
    {
      "name": "vite:import-glob",
      "start": 1761251141280,
      "end": 1761251141280,
      "order": "normal"
    },
    {
      "name": "nuxt:composable-keys",
      "start": 1761251141280,
      "end": 1761251141280,
      "order": "post"
    },
    {
      "name": "nuxt:composable-keys",
      "start": 1761251141280,
      "end": 1761251141280,
      "order": "post"
    },
    {
      "name": "unhead:remove-server-composables",
      "start": 1761251141280,
      "end": 1761251141280,
      "order": "post"
    },
    {
      "name": "unhead:use-seo-meta-transform",
      "start": 1761251141280,
      "end": 1761251141280,
      "order": "post"
    },
    {
      "name": "unhead:use-seo-meta-transform",
      "start": 1761251141280,
      "end": 1761251141280,
      "order": "post"
    },
    {
      "name": "nuxt:imports-transform",
      "start": 1761251141280,
      "end": 1761251141280,
      "order": "post"
    },
    {
      "name": "nuxt:imports-transform",
      "start": 1761251141280,
      "end": 1761251141280,
      "order": "post"
    },
    {
      "name": "unctx:transform",
      "start": 1761251141280,
      "end": 1761251141280,
      "order": "post"
    },
    {
      "name": "unctx:transform",
      "start": 1761251141280,
      "end": 1761251141280,
      "order": "post"
    },
    {
      "name": "nuxt:pages-macros-transform",
      "start": 1761251141280,
      "end": 1761251141280,
      "order": "post"
    },
    {
      "name": "nuxt:pages-macros-transform",
      "start": 1761251141280,
      "end": 1761251141280,
      "order": "post"
    },
    {
      "name": "nuxt:tree-shake-template",
      "start": 1761251141280,
      "end": 1761251141280,
      "order": "post"
    },
    {
      "name": "nuxt:components-loader",
      "start": 1761251141280,
      "end": 1761251141280,
      "order": "post"
    },
    {
      "name": "nuxt:tree-shake-composables:transform",
      "start": 1761251141280,
      "end": 1761251141280,
      "order": "post"
    },
    {
      "name": "vite:build-import-analysis",
      "start": 1761251141281,
      "end": 1761251141281,
      "order": "normal"
    },
    {
      "name": "vite:reporter",
      "start": 1761251141281,
      "end": 1761251141281,
      "order": "normal"
    }
  ]
}
