{
  "resolvedId": "/Users/amerusfinancial/Desktop/projects/Amerus/app/components/services/sidebars/HomeSidebar.vue?nuxt_component=async&nuxt_component_name=HomeSidebar",
  "transforms": [
    {
      "name": "vite:load-fallback",
      "result": "<template>\n  <aside\n    class=\"bg-gray-50 rounded-2xl border border-gray-200 sticky top-24 h-fit shadow-sm hover:shadow-md transition-shadow duration-300\"\n  >\n    <!-- Header -->\n    <header\n      class=\"flex items-center gap-3 bg-[#30BCFE] text-white p-5 rounded-t-2xl\"\n    >\n      <Icon name=\"lucide:heart-pulse\" size=\"80\" class=\"text-white\" />\n      <h3 class=\"text-2xl font-semibold\">Explore Health Insurance</h3>\n    </header>\n\n    <!-- Body -->\n    <div class=\"p-6\">\n      <!-- Navigation Links -->\n      <ul class=\"space-y-1\">\n        <li\n          v-for=\"(link, index) in links\"\n          :key=\"link.href\"\n          class=\"group py-2 px-3 rounded-lg transition-all duration-300 hover:bg-white hover:shadow-sm\"\n          :class=\"{ 'border-b border-gray-200': index !== links.length - 1 }\"\n        >\n          <NuxtLink\n            :to=\"link.href\"\n            class=\"flex items-center justify-between text-gray-700 group-hover:text-[#30BCFE] transition-colors duration-300\"\n          >\n            <div class=\"flex items-center\">\n              <div\n                class=\"p-2 bg-[#30BCFE]/10 rounded-md mr-3 flex items-center justify-center transition-transform duration-300 group-hover:scale-110\"\n              >\n                <Icon :name=\"link.icon\" class=\"text-[#30BCFE]\" size=\"25\" />\n              </div>\n              <span class=\"font-medium\">{{ link.label }}</span>\n            </div>\n\n            <!-- Badge -->\n            <span\n              v-if=\"link.badge\"\n              class=\"ml-2 inline-flex items-center rounded-full bg-green-100 text-green-800 text-xs font-medium px-2 py-0.5\"\n            >\n              {{ link.badge }}\n            </span>\n          </NuxtLink>\n        </li>\n      </ul>\n\n      <!-- CTA Card -->\n      <div\n        class=\"mt-8 bg-blue-50 rounded-xl p-6 border border-blue-100 transition-all duration-300 hover:shadow-sm\"\n      >\n        <h4 class=\"font-semibold mb-2 text-gray-800 flex items-center gap-2\">\n          <Icon name=\"lucide:help-circle\" class=\"text-[#30BCFE]\" size=\"20\" />\n          Have Questions?\n        </h4>\n\n        <p class=\"text-sm text-gray-600 mb-5 leading-relaxed\">\n          Our specialists can help you understand your options and find the right\n          coverage for your needs.\n        </p>\n\n        <NuxtLink to=\"/contact\">\n          <button\n            class=\"w-full inline-flex items-center justify-center gap-2 rounded-lg text-sm font-semibold bg-[#30BCFE] text-white hover:bg-[#30BCFE]/90 transition-all duration-300 h-11 shadow-sm hover:shadow-md\"\n          >\n            <Icon name=\"lucide:phone\" class=\"h-4 w-4\" />\n            Contact an Advisor\n          </button>\n        </NuxtLink>\n      </div>\n    </div>\n  </aside>\n</template>\n\n<script setup>\nconst links = [\n  { href: \"/services/health/individual-health\", label: \"Individual Health\", icon: \"lucide:user-plus\" },\n  { href: \"/services/health/family-coverage\", label: \"Family Coverage\", icon: \"lucide:users\" },\n  { href: \"/services/health/group-health\", label: \"Group Health\", icon: \"lucide:users\" },\n  { href: \"/services/health/medicare\", label: \"Medicare\", icon: \"lucide:activity\" },\n  { href: \"/services/health/dental\", label: \"Dental Insurance\", icon: \"lucide:stethoscope\" },\n  { href: \"/services/health/senior-dental\", label: \"Senior Dental\", icon: \"lucide:stethoscope\" },\n  { href: \"/services/health/vision-coverage\", label: \"Vision Coverage\", icon: \"lucide:eye\" },\n  { href: \"/guides/medicare-guide\", label: \"Medicare Guide\", icon: \"lucide:file-text\" },\n  {\n    href: \"/blog/health-insurance-networks\",\n    label: \"In-Network vs. Out-of-Network\",\n    icon: \"lucide:shield\",\n    badge: \"New\",\n  },\n];\n</script>\n",
      "start": 1761251141937,
      "end": 1761251142107,
      "sourcemaps": null
    },
    {
      "name": "nuxt:layer-aliasing",
      "start": 1761251142107,
      "end": 1761251142107,
      "order": "pre"
    },
    {
      "name": "nuxt:layer-aliasing",
      "start": 1761251142107,
      "end": 1761251142107,
      "order": "pre"
    },
    {
      "name": "nuxt:server-devonly:transform",
      "start": 1761251142107,
      "end": 1761251142107,
      "order": "pre"
    },
    {
      "name": "nuxt:server-devonly:transform",
      "start": 1761251142107,
      "end": 1761251142107,
      "order": "pre"
    },
    {
      "name": "content-slot",
      "start": 1761251142107,
      "end": 1761251142107,
      "order": "pre"
    },
    {
      "name": "content-slot",
      "start": 1761251142107,
      "end": 1761251142107,
      "order": "pre"
    },
    {
      "name": "nuxt:client-fallback-auto-id",
      "start": 1761251142107,
      "end": 1761251142107,
      "order": "pre"
    },
    {
      "name": "server-only-component-transform",
      "start": 1761251142107,
      "end": 1761251142107,
      "order": "pre"
    },
    {
      "name": "vite:css",
      "start": 1761251142107,
      "end": 1761251142107,
      "order": "normal"
    },
    {
      "name": "vite:esbuild",
      "start": 1761251142107,
      "end": 1761251142107,
      "order": "normal"
    },
    {
      "name": "vite:json",
      "start": 1761251142107,
      "end": 1761251142107,
      "order": "normal"
    },
    {
      "name": "vite:worker",
      "start": 1761251142107,
      "end": 1761251142107,
      "order": "normal"
    },
    {
      "name": "vite:vue",
      "result": "import { resolveComponent as _resolveComponent, withCtx as _withCtx, createVNode as _createVNode, toDisplayString as _toDisplayString, openBlock as _openBlock, createBlock as _createBlock, createCommentVNode as _createCommentVNode, createTextVNode as _createTextVNode, mergeProps as _mergeProps } from \"vue\"\nimport { ssrRenderComponent as _ssrRenderComponent, ssrRenderClass as _ssrRenderClass, ssrRenderAttrs as _ssrRenderAttrs, ssrInterpolate as _ssrInterpolate, ssrRenderList as _ssrRenderList } from \"vue/server-renderer\"\n\n\nconst _sfc_main = {\n  __name: 'HomeSidebar',\n  __ssrInlineRender: true,\n  setup(__props) {\n\nconst links = [\n  { href: \"/services/health/individual-health\", label: \"Individual Health\", icon: \"lucide:user-plus\" },\n  { href: \"/services/health/family-coverage\", label: \"Family Coverage\", icon: \"lucide:users\" },\n  { href: \"/services/health/group-health\", label: \"Group Health\", icon: \"lucide:users\" },\n  { href: \"/services/health/medicare\", label: \"Medicare\", icon: \"lucide:activity\" },\n  { href: \"/services/health/dental\", label: \"Dental Insurance\", icon: \"lucide:stethoscope\" },\n  { href: \"/services/health/senior-dental\", label: \"Senior Dental\", icon: \"lucide:stethoscope\" },\n  { href: \"/services/health/vision-coverage\", label: \"Vision Coverage\", icon: \"lucide:eye\" },\n  { href: \"/guides/medicare-guide\", label: \"Medicare Guide\", icon: \"lucide:file-text\" },\n  {\n    href: \"/blog/health-insurance-networks\",\n    label: \"In-Network vs. Out-of-Network\",\n    icon: \"lucide:shield\",\n    badge: \"New\",\n  },\n];\n\nreturn (_ctx, _push, _parent, _attrs) => {\n  const _component_Icon = _resolveComponent(\"Icon\")\n  const _component_NuxtLink = _resolveComponent(\"NuxtLink\")\n\n  _push(`<aside${_ssrRenderAttrs(_mergeProps({ class: \"bg-gray-50 rounded-2xl border border-gray-200 sticky top-24 h-fit shadow-sm hover:shadow-md transition-shadow duration-300\" }, _attrs))}><header class=\"flex items-center gap-3 bg-[#30BCFE] text-white p-5 rounded-t-2xl\">`)\n  _push(_ssrRenderComponent(_component_Icon, {\n    name: \"lucide:heart-pulse\",\n    size: \"80\",\n    class: \"text-white\"\n  }, null, _parent))\n  _push(`<h3 class=\"text-2xl font-semibold\">Explore Health Insurance</h3></header><div class=\"p-6\"><ul class=\"space-y-1\"><!--[-->`)\n  _ssrRenderList(links, (link, index) => {\n    _push(`<li class=\"${_ssrRenderClass([{ 'border-b border-gray-200': index !== links.length - 1 }, \"group py-2 px-3 rounded-lg transition-all duration-300 hover:bg-white hover:shadow-sm\"])}\">`)\n    _push(_ssrRenderComponent(_component_NuxtLink, {\n      to: link.href,\n      class: \"flex items-center justify-between text-gray-700 group-hover:text-[#30BCFE] transition-colors duration-300\"\n    }, {\n      default: _withCtx((_, _push, _parent, _scopeId) => {\n        if (_push) {\n          _push(`<div class=\"flex items-center\"${\n            _scopeId\n          }><div class=\"p-2 bg-[#30BCFE]/10 rounded-md mr-3 flex items-center justify-center transition-transform duration-300 group-hover:scale-110\"${\n            _scopeId\n          }>`)\n          _push(_ssrRenderComponent(_component_Icon, {\n            name: link.icon,\n            class: \"text-[#30BCFE]\",\n            size: \"25\"\n          }, null, _parent, _scopeId))\n          _push(`</div><span class=\"font-medium\"${\n            _scopeId\n          }>${\n            _ssrInterpolate(link.label)\n          }</span></div>`)\n          if (link.badge) {\n            _push(`<span class=\"ml-2 inline-flex items-center rounded-full bg-green-100 text-green-800 text-xs font-medium px-2 py-0.5\"${\n              _scopeId\n            }>${\n              _ssrInterpolate(link.badge)\n            }</span>`)\n          } else {\n            _push(`<!---->`)\n          }\n        } else {\n          return [\n            _createVNode(\"div\", { class: \"flex items-center\" }, [\n              _createVNode(\"div\", { class: \"p-2 bg-[#30BCFE]/10 rounded-md mr-3 flex items-center justify-center transition-transform duration-300 group-hover:scale-110\" }, [\n                _createVNode(_component_Icon, {\n                  name: link.icon,\n                  class: \"text-[#30BCFE]\",\n                  size: \"25\"\n                }, null, 8, [\"name\"])\n              ]),\n              _createVNode(\"span\", { class: \"font-medium\" }, _toDisplayString(link.label), 1)\n            ]),\n            (link.badge)\n              ? (_openBlock(), _createBlock(\"span\", {\n                  key: 0,\n                  class: \"ml-2 inline-flex items-center rounded-full bg-green-100 text-green-800 text-xs font-medium px-2 py-0.5\"\n                }, _toDisplayString(link.badge), 1))\n              : _createCommentVNode(\"\", true)\n          ]\n        }\n      }),\n      _: 2\n    }, _parent))\n    _push(`</li>`)\n  })\n  _push(`<!--]--></ul><div class=\"mt-8 bg-blue-50 rounded-xl p-6 border border-blue-100 transition-all duration-300 hover:shadow-sm\"><h4 class=\"font-semibold mb-2 text-gray-800 flex items-center gap-2\">`)\n  _push(_ssrRenderComponent(_component_Icon, {\n    name: \"lucide:help-circle\",\n    class: \"text-[#30BCFE]\",\n    size: \"20\"\n  }, null, _parent))\n  _push(` Have Questions? </h4><p class=\"text-sm text-gray-600 mb-5 leading-relaxed\"> Our specialists can help you understand your options and find the right coverage for your needs. </p>`)\n  _push(_ssrRenderComponent(_component_NuxtLink, { to: \"/contact\" }, {\n    default: _withCtx((_, _push, _parent, _scopeId) => {\n      if (_push) {\n        _push(`<button class=\"w-full inline-flex items-center justify-center gap-2 rounded-lg text-sm font-semibold bg-[#30BCFE] text-white hover:bg-[#30BCFE]/90 transition-all duration-300 h-11 shadow-sm hover:shadow-md\"${_scopeId}>`)\n        _push(_ssrRenderComponent(_component_Icon, {\n          name: \"lucide:phone\",\n          class: \"h-4 w-4\"\n        }, null, _parent, _scopeId))\n        _push(` Contact an Advisor </button>`)\n      } else {\n        return [\n          _createVNode(\"button\", { class: \"w-full inline-flex items-center justify-center gap-2 rounded-lg text-sm font-semibold bg-[#30BCFE] text-white hover:bg-[#30BCFE]/90 transition-all duration-300 h-11 shadow-sm hover:shadow-md\" }, [\n            _createVNode(_component_Icon, {\n              name: \"lucide:phone\",\n              class: \"h-4 w-4\"\n            }),\n            _createTextVNode(\" Contact an Advisor \")\n          ])\n        ]\n      }\n    }),\n    _: 1\n  }, _parent))\n  _push(`</div></div></aside>`)\n}\n}\n\n}\n\n\n\nimport { useSSRContext as __vite_useSSRContext } from 'vue'\nconst _sfc_setup = _sfc_main.setup\n_sfc_main.setup = (props, ctx) => {\n  const ssrContext = __vite_useSSRContext()\n  ;(ssrContext.modules || (ssrContext.modules = new Set())).add(\"components/services/sidebars/HomeSidebar.vue\")\n  return _sfc_setup ? _sfc_setup(props, ctx) : undefined\n}\nexport default _sfc_main",
      "start": 1761251142107,
      "end": 1761251142109,
      "order": "normal",
      "sourcemaps": {
        "version": 3,
        "sources": [
          "/Users/amerusfinancial/Desktop/projects/Amerus/app/components/services/sidebars/HomeSidebar.vue"
        ],
        "sourcesContent": [
          "<template>\n  <aside\n    class=\"bg-gray-50 rounded-2xl border border-gray-200 sticky top-24 h-fit shadow-sm hover:shadow-md transition-shadow duration-300\"\n  >\n    <!-- Header -->\n    <header\n      class=\"flex items-center gap-3 bg-[#30BCFE] text-white p-5 rounded-t-2xl\"\n    >\n      <Icon name=\"lucide:heart-pulse\" size=\"80\" class=\"text-white\" />\n      <h3 class=\"text-2xl font-semibold\">Explore Health Insurance</h3>\n    </header>\n\n    <!-- Body -->\n    <div class=\"p-6\">\n      <!-- Navigation Links -->\n      <ul class=\"space-y-1\">\n        <li\n          v-for=\"(link, index) in links\"\n          :key=\"link.href\"\n          class=\"group py-2 px-3 rounded-lg transition-all duration-300 hover:bg-white hover:shadow-sm\"\n          :class=\"{ 'border-b border-gray-200': index !== links.length - 1 }\"\n        >\n          <NuxtLink\n            :to=\"link.href\"\n            class=\"flex items-center justify-between text-gray-700 group-hover:text-[#30BCFE] transition-colors duration-300\"\n          >\n            <div class=\"flex items-center\">\n              <div\n                class=\"p-2 bg-[#30BCFE]/10 rounded-md mr-3 flex items-center justify-center transition-transform duration-300 group-hover:scale-110\"\n              >\n                <Icon :name=\"link.icon\" class=\"text-[#30BCFE]\" size=\"25\" />\n              </div>\n              <span class=\"font-medium\">{{ link.label }}</span>\n            </div>\n\n            <!-- Badge -->\n            <span\n              v-if=\"link.badge\"\n              class=\"ml-2 inline-flex items-center rounded-full bg-green-100 text-green-800 text-xs font-medium px-2 py-0.5\"\n            >\n              {{ link.badge }}\n            </span>\n          </NuxtLink>\n        </li>\n      </ul>\n\n      <!-- CTA Card -->\n      <div\n        class=\"mt-8 bg-blue-50 rounded-xl p-6 border border-blue-100 transition-all duration-300 hover:shadow-sm\"\n      >\n        <h4 class=\"font-semibold mb-2 text-gray-800 flex items-center gap-2\">\n          <Icon name=\"lucide:help-circle\" class=\"text-[#30BCFE]\" size=\"20\" />\n          Have Questions?\n        </h4>\n\n        <p class=\"text-sm text-gray-600 mb-5 leading-relaxed\">\n          Our specialists can help you understand your options and find the right\n          coverage for your needs.\n        </p>\n\n        <NuxtLink to=\"/contact\">\n          <button\n            class=\"w-full inline-flex items-center justify-center gap-2 rounded-lg text-sm font-semibold bg-[#30BCFE] text-white hover:bg-[#30BCFE]/90 transition-all duration-300 h-11 shadow-sm hover:shadow-md\"\n          >\n            <Icon name=\"lucide:phone\" class=\"h-4 w-4\" />\n            Contact an Advisor\n          </button>\n        </NuxtLink>\n      </div>\n    </div>\n  </aside>\n</template>\n\n<script setup>\nconst links = [\n  { href: \"/services/health/individual-health\", label: \"Individual Health\", icon: \"lucide:user-plus\" },\n  { href: \"/services/health/family-coverage\", label: \"Family Coverage\", icon: \"lucide:users\" },\n  { href: \"/services/health/group-health\", label: \"Group Health\", icon: \"lucide:users\" },\n  { href: \"/services/health/medicare\", label: \"Medicare\", icon: \"lucide:activity\" },\n  { href: \"/services/health/dental\", label: \"Dental Insurance\", icon: \"lucide:stethoscope\" },\n  { href: \"/services/health/senior-dental\", label: \"Senior Dental\", icon: \"lucide:stethoscope\" },\n  { href: \"/services/health/vision-coverage\", label: \"Vision Coverage\", icon: \"lucide:eye\" },\n  { href: \"/guides/medicare-guide\", label: \"Medicare Guide\", icon: \"lucide:file-text\" },\n  {\n    href: \"/blog/health-insurance-networks\",\n    label: \"In-Network vs. Out-of-Network\",\n    icon: \"lucide:shield\",\n    badge: \"New\",\n  },\n];\n</script>\n"
        ],
        "names": [],
        "mappings": ";;;;;;;;AAyEc;AACd,CAAC,CAAC,CAAC,CAAC,CAAC,CAAC,CAAC,CAAC,CAAC,CAAC,CAAC,CAAC,CAAC,CAAC,CAAC;AACf,CAAC,CAAC,CAAC,CAAC,CAAC,CAAC,CAAC,CAAC,CAAC,CAAC,CAAC,CAAC,CAAC,CAAC,CAAC,CAAC,CAAC,CAAC,CAAC,CAAC,CAAC,CAAC,CAAC,CAAC,CAAC,CAAC,CAAC,CAAC,CAAC,CAAC,CAAC,CAAC,CAAC,CAAC,CAAC,CAAC,CAAC,CAAC,CAAC,CAAC,CAAC,CAAC,CAAC,CAAC,CAAC,CAAC,CAAC,CAAC,CAAC,CAAC,CAAC,CAAC,CAAC,CAAC,CAAC,CAAC,CAAC,CAAC,CAAC,CAAC,CAAC,CAAC,CAAC,CAAC,CAAC,CAAC,CAAC,CAAC,CAAC,CAAC,CAAC,CAAC,CAAC,CAAC,CAAC,CAAC,CAAC,CAAC,CAAC,CAAC,CAAC,CAAC,CAAC,CAAC,CAAC,CAAC,CAAC,CAAC,CAAC,CAAC,CAAC,CAAC,CAAC,CAAC,CAAC,CAAC,CAAC,CAAC,CAAC,CAAC,CAAC,CAAC,CAAC;AACvG,CAAC,CAAC,CAAC,CAAC,CAAC,CAAC,CAAC,CAAC,CAAC,CAAC,CAAC,CAAC,CAAC,CAAC,CAAC,CAAC,CAAC,CAAC,CAAC,CAAC,CAAC,CAAC,CAAC,CAAC,CAAC,CAAC,CAAC,CAAC,CAAC,CAAC,CAAC,CAAC,CAAC,CAAC,CAAC,CAAC,CAAC,CAAC,CAAC,CAAC,CAAC,CAAC,CAAC,CAAC,CAAC,CAAC,CAAC,CAAC,CAAC,CAAC,CAAC,CAAC,CAAC,CAAC,CAAC,CAAC,CAAC,CAAC,CAAC,CAAC,CAAC,CAAC,CAAC,CAAC,CAAC,CAAC,CAAC,CAAC,CAAC,CAAC,CAAC,CAAC,CAAC,CAAC,CAAC,CAAC,CAAC,CAAC,CAAC,CAAC,CAAC,CAAC,CAAC,CAAC,CAAC,CAAC,CAAC,CAAC,CAAC,CAAC,CAAC,CAAC,CAAC,CAAC,CAAC;AAC/F,CAAC,CAAC,CAAC,CAAC,CAAC,CAAC,CAAC,CAAC,CAAC,CAAC,CAAC,CAAC,CAAC,CAAC,CAAC,CAAC,CAAC,CAAC,CAAC,CAAC,CAAC,CAAC,CAAC,CAAC,CAAC,CAAC,CAAC,CAAC,CAAC,CAAC,CAAC,CAAC,CAAC,CAAC,CAAC,CAAC,CAAC,CAAC,CAAC,CAAC,CAAC,CAAC,CAAC,CAAC,CAAC,CAAC,CAAC,CAAC,CAAC,CAAC,CAAC,CAAC,CAAC,CAAC,CAAC,CAAC,CAAC,CAAC,CAAC,CAAC,CAAC,CAAC,CAAC,CAAC,CAAC,CAAC,CAAC,CAAC,CAAC,CAAC,CAAC,CAAC,CAAC,CAAC,CAAC,CAAC,CAAC,CAAC,CAAC,CAAC,CAAC,CAAC,CAAC,CAAC,CAAC,CAAC,CAAC,CAAC,CAAC;AACzF,CAAC,CAAC,CAAC,CAAC,CAAC,CAAC,CAAC,CAAC,CAAC,CAAC,CAAC,CAAC,CAAC,CAAC,CAAC,CAAC,CAAC,CAAC,CAAC,CAAC,CAAC,CAAC,CAAC,CAAC,CAAC,CAAC,CAAC,CAAC,CAAC,CAAC,CAAC,CAAC,CAAC,CAAC,CAAC,CAAC,CAAC,CAAC,CAAC,CAAC,CAAC,CAAC,CAAC,CAAC,CAAC,CAAC,CAAC,CAAC,CAAC,CAAC,CAAC,CAAC,CAAC,CAAC,CAAC,CAAC,CAAC,CAAC,CAAC,CAAC,CAAC,CAAC,CAAC,CAAC,CAAC,CAAC,CAAC,CAAC,CAAC,CAAC,CAAC,CAAC,CAAC,CAAC,CAAC,CAAC,CAAC,CAAC,CAAC,CAAC,CAAC,CAAC,CAAC,CAAC;AACpF,CAAC,CAAC,CAAC,CAAC,CAAC,CAAC,CAAC,CAAC,CAAC,CAAC,CAAC,CAAC,CAAC,CAAC,CAAC,CAAC,CAAC,CAAC,CAAC,CAAC,CAAC,CAAC,CAAC,CAAC,CAAC,CAAC,CAAC,CAAC,CAAC,CAAC,CAAC,CAAC,CAAC,CAAC,CAAC,CAAC,CAAC,CAAC,CAAC,CAAC,CAAC,CAAC,CAAC,CAAC,CAAC,CAAC,CAAC,CAAC,CAAC,CAAC,CAAC,CAAC,CAAC,CAAC,CAAC,CAAC,CAAC,CAAC,CAAC,CAAC,CAAC,CAAC,CAAC,CAAC,CAAC,CAAC,CAAC,CAAC,CAAC,CAAC,CAAC,CAAC,CAAC,CAAC,CAAC,CAAC,CAAC,CAAC,CAAC,CAAC,CAAC,CAAC,CAAC,CAAC,CAAC,CAAC,CAAC,CAAC,CAAC,CAAC,CAAC,CAAC,CAAC;AAC7F,CAAC,CAAC,CAAC,CAAC,CAAC,CAAC,CAAC,CAAC,CAAC,CAAC,CAAC,CAAC,CAAC,CAAC,CAAC,CAAC,CAAC,CAAC,CAAC,CAAC,CAAC,CAAC,CAAC,CAAC,CAAC,CAAC,CAAC,CAAC,CAAC,CAAC,CAAC,CAAC,CAAC,CAAC,CAAC,CAAC,CAAC,CAAC,CAAC,CAAC,CAAC,CAAC,CAAC,CAAC,CAAC,CAAC,CAAC,CAAC,CAAC,CAAC,CAAC,CAAC,CAAC,CAAC,CAAC,CAAC,CAAC,CAAC,CAAC,CAAC,CAAC,CAAC,CAAC,CAAC,CAAC,CAAC,CAAC,CAAC,CAAC,CAAC,CAAC,CAAC,CAAC,CAAC,CAAC,CAAC,CAAC,CAAC,CAAC,CAAC,CAAC,CAAC,CAAC,CAAC,CAAC,CAAC,CAAC,CAAC,CAAC,CAAC,CAAC,CAAC,CAAC,CAAC,CAAC,CAAC,CAAC;AACjG,CAAC,CAAC,CAAC,CAAC,CAAC,CAAC,CAAC,CAAC,CAAC,CAAC,CAAC,CAAC,CAAC,CAAC,CAAC,CAAC,CAAC,CAAC,CAAC,CAAC,CAAC,CAAC,CAAC,CAAC,CAAC,CAAC,CAAC,CAAC,CAAC,CAAC,CAAC,CAAC,CAAC,CAAC,CAAC,CAAC,CAAC,CAAC,CAAC,CAAC,CAAC,CAAC,CAAC,CAAC,CAAC,CAAC,CAAC,CAAC,CAAC,CAAC,CAAC,CAAC,CAAC,CAAC,CAAC,CAAC,CAAC,CAAC,CAAC,CAAC,CAAC,CAAC,CAAC,CAAC,CAAC,CAAC,CAAC,CAAC,CAAC,CAAC,CAAC,CAAC,CAAC,CAAC,CAAC,CAAC,CAAC,CAAC,CAAC,CAAC,CAAC,CAAC,CAAC,CAAC,CAAC,CAAC,CAAC,CAAC,CAAC,CAAC,CAAC,CAAC,CAAC;AAC7F,CAAC,CAAC,CAAC,CAAC,CAAC,CAAC,CAAC,CAAC,CAAC,CAAC,CAAC,CAAC,CAAC,CAAC,CAAC,CAAC,CAAC,CAAC,CAAC,CAAC,CAAC,CAAC,CAAC,CAAC,CAAC,CAAC,CAAC,CAAC,CAAC,CAAC,CAAC,CAAC,CAAC,CAAC,CAAC,CAAC,CAAC,CAAC,CAAC,CAAC,CAAC,CAAC,CAAC,CAAC,CAAC,CAAC,CAAC,CAAC,CAAC,CAAC,CAAC,CAAC,CAAC,CAAC,CAAC,CAAC,CAAC,CAAC,CAAC,CAAC,CAAC,CAAC,CAAC,CAAC,CAAC,CAAC,CAAC,CAAC,CAAC,CAAC,CAAC,CAAC,CAAC,CAAC,CAAC,CAAC,CAAC,CAAC,CAAC,CAAC,CAAC,CAAC,CAAC,CAAC,CAAC,CAAC,CAAC,CAAC;AACxF,CAAC,CAAC,CAAC;AACH,CAAC,CAAC,CAAC,CAAC,CAAC,CAAC,CAAC,CAAC,CAAC,CAAC,CAAC,CAAC,CAAC,CAAC,CAAC,CAAC,CAAC,CAAC,CAAC,CAAC,CAAC,CAAC,CAAC,CAAC,CAAC,CAAC,CAAC,CAAC,CAAC,CAAC,CAAC,CAAC,CAAC,CAAC,CAAC,CAAC,CAAC,CAAC,CAAC,CAAC,CAAC,CAAC,CAAC,CAAC;AAC5C,CAAC,CAAC,CAAC,CAAC,CAAC,CAAC,CAAC,CAAC,CAAC,CAAC,CAAC,CAAC,CAAC,CAAC,CAAC,CAAC,CAAC,CAAC,CAAC,CAAC,CAAC,CAAC,CAAC,CAAC,CAAC,CAAC,CAAC,CAAC,CAAC,CAAC,CAAC,CAAC,CAAC,CAAC,CAAC,CAAC,CAAC,CAAC,CAAC,CAAC,CAAC,CAAC,CAAC;AAC3C,CAAC,CAAC,CAAC,CAAC,CAAC,CAAC,CAAC,CAAC,CAAC,CAAC,CAAC,CAAC,CAAC,CAAC,CAAC,CAAC,CAAC,CAAC,CAAC,CAAC,CAAC,CAAC,CAAC,CAAC,CAAC,CAAC;AAC1B,CAAC,CAAC,CAAC,CAAC,CAAC,CAAC,CAAC,CAAC,CAAC,CAAC,CAAC,CAAC,CAAC,CAAC,CAAC,CAAC,CAAC;AACjB,CAAC,CAAC,CAAC,CAAC;AACJ,CAAC,CAAC;;;;;;;;;;;;;;;;;;;;;;;;;;;;;;;;;;;;;;;;;;;;;;;;;;;;;;;;;;;;;;;;;;;;;;;;;;;;;;;;;;;;;;;;;;;;;;;;;;;;;;;;"
      }
    },
    {
      "name": "vite:vue-jsx",
      "start": 1761251142109,
      "end": 1761251142109,
      "order": "normal"
    },
    {
      "name": "replace",
      "start": 1761251142109,
      "end": 1761251142109,
      "order": "normal"
    },
    {
      "name": "replace",
      "start": 1761251142109,
      "end": 1761251142109,
      "order": "normal"
    },
    {
      "name": "nuxt:remove-plugin-metadata",
      "start": 1761251142110,
      "end": 1761251142110,
      "order": "normal"
    },
    {
      "name": "nuxt:remove-plugin-metadata",
      "start": 1761251142110,
      "end": 1761251142110,
      "order": "normal"
    },
    {
      "name": "nuxt:components:imports",
      "result": "import { defineAsyncComponent } from \"vue\"\nexport default defineAsyncComponent(() => import(\"/Users/amerusfinancial/Desktop/projects/Amerus/app/components/services/sidebars/HomeSidebar.vue\").then(r => r.default))",
      "start": 1761251142110,
      "end": 1761251142110,
      "order": "normal",
      "sourcemaps": null
    },
    {
      "name": "replace",
      "start": 1761251142110,
      "end": 1761251142110,
      "order": "normal"
    },
    {
      "name": "ssr-styles",
      "start": 1761251142110,
      "end": 1761251142110,
      "order": "normal"
    },
    {
      "name": "vite:define",
      "start": 1761251142110,
      "end": 1761251142110,
      "order": "normal"
    },
    {
      "name": "vite:css-post",
      "start": 1761251142110,
      "end": 1761251142110,
      "order": "normal"
    },
    {
      "name": "vite:build-html",
      "start": 1761251142110,
      "end": 1761251142110,
      "order": "normal"
    },
    {
      "name": "vite:worker-import-meta-url",
      "start": 1761251142110,
      "end": 1761251142110,
      "order": "normal"
    },
    {
      "name": "vite:asset-import-meta-url",
      "start": 1761251142110,
      "end": 1761251142110,
      "order": "normal"
    },
    {
      "name": "commonjs",
      "start": 1761251142110,
      "end": 1761251142110,
      "order": "normal"
    },
    {
      "name": "vite:dynamic-import-vars",
      "start": 1761251142110,
      "end": 1761251142110,
      "order": "normal"
    },
    {
      "name": "vite:import-glob",
      "start": 1761251142110,
      "end": 1761251142110,
      "order": "normal"
    },
    {
      "name": "nuxt:composable-keys",
      "start": 1761251142110,
      "end": 1761251142110,
      "order": "post"
    },
    {
      "name": "nuxt:composable-keys",
      "start": 1761251142110,
      "end": 1761251142110,
      "order": "post"
    },
    {
      "name": "unhead:remove-server-composables",
      "start": 1761251142110,
      "end": 1761251142110,
      "order": "post"
    },
    {
      "name": "unhead:use-seo-meta-transform",
      "start": 1761251142110,
      "end": 1761251142110,
      "order": "post"
    },
    {
      "name": "unhead:use-seo-meta-transform",
      "start": 1761251142110,
      "end": 1761251142110,
      "order": "post"
    },
    {
      "name": "nuxt:imports-transform",
      "start": 1761251142110,
      "end": 1761251142110,
      "order": "post"
    },
    {
      "name": "nuxt:imports-transform",
      "start": 1761251142110,
      "end": 1761251142110,
      "order": "post"
    },
    {
      "name": "unctx:transform",
      "start": 1761251142110,
      "end": 1761251142110,
      "order": "post"
    },
    {
      "name": "unctx:transform",
      "start": 1761251142110,
      "end": 1761251142110,
      "order": "post"
    },
    {
      "name": "nuxt:pages-macros-transform",
      "start": 1761251142110,
      "end": 1761251142110,
      "order": "post"
    },
    {
      "name": "nuxt:pages-macros-transform",
      "start": 1761251142110,
      "end": 1761251142110,
      "order": "post"
    },
    {
      "name": "nuxt:tree-shake-template",
      "start": 1761251142110,
      "end": 1761251142110,
      "order": "post"
    },
    {
      "name": "nuxt:components-loader",
      "start": 1761251142110,
      "end": 1761251142110,
      "order": "post"
    },
    {
      "name": "nuxt:tree-shake-composables:transform",
      "start": 1761251142110,
      "end": 1761251142110,
      "order": "post"
    },
    {
      "name": "vite:build-import-analysis",
      "start": 1761251142110,
      "end": 1761251142110,
      "order": "normal"
    },
    {
      "name": "vite:reporter",
      "start": 1761251142110,
      "end": 1761251142110,
      "order": "normal"
    }
  ]
}
